odoo/addons/sale_commission_product_criteria_fiscal_position_type/README.rst
odoo/addons/sale_commission_product_criteria_fiscal_position_type/__init__.py
odoo/addons/sale_commission_product_criteria_fiscal_position_type/__manifest__.py
odoo/addons/sale_commission_product_criteria_fiscal_position_type/i18n/es.po
odoo/addons/sale_commission_product_criteria_fiscal_position_type/i18n/it.po
odoo/addons/sale_commission_product_criteria_fiscal_position_type/i18n/pt_BR.po
odoo/addons/sale_commission_product_criteria_fiscal_position_type/i18n/sale_commission_product_criteria_fiscal_position_type.pot
odoo/addons/sale_commission_product_criteria_fiscal_position_type/models/__init__.py
odoo/addons/sale_commission_product_criteria_fiscal_position_type/models/account_invoice_line_agent.py
odoo/addons/sale_commission_product_criteria_fiscal_position_type/models/commission_item.py
odoo/addons/sale_commission_product_criteria_fiscal_position_type/models/commission_line_mixin.py
odoo/addons/sale_commission_product_criteria_fiscal_position_type/models/sale_order_line_agent.py
odoo/addons/sale_commission_product_criteria_fiscal_position_type/readme/CONTRIBUTORS.md
odoo/addons/sale_commission_product_criteria_fiscal_position_type/readme/DESCRIPTION.md
odoo/addons/sale_commission_product_criteria_fiscal_position_type/readme/USAGE.md
odoo/addons/sale_commission_product_criteria_fiscal_position_type/static/description/icon.png
odoo/addons/sale_commission_product_criteria_fiscal_position_type/static/description/icon.svg
odoo/addons/sale_commission_product_criteria_fiscal_position_type/static/description/index.html
odoo/addons/sale_commission_product_criteria_fiscal_position_type/tests/__init__.py
odoo/addons/sale_commission_product_criteria_fiscal_position_type/tests/test_sale_commission_product_criteria_fiscal_position_type.py
odoo/addons/sale_commission_product_criteria_fiscal_position_type/views/commission_item_views.xml
odoo_addon_sale_commission_product_criteria_fiscal_position_type-16.0.1.0.0.5.dist-info/METADATA
odoo_addon_sale_commission_product_criteria_fiscal_position_type-16.0.1.0.0.5.dist-info/WHEEL
odoo_addon_sale_commission_product_criteria_fiscal_position_type-16.0.1.0.0.5.dist-info/top_level.txt
odoo_addon_sale_commission_product_criteria_fiscal_position_type-16.0.1.0.0.5.dist-info/RECORD
